multiprocess/__init__.py
multiprocess/multiprocessClass.py
multiprocess/multiprocessFunc.py
multiprocessing_wrap-0.0.3.dist-info/METADATA
multiprocessing_wrap-0.0.3.dist-info/WHEEL
multiprocessing_wrap-0.0.3.dist-info/top_level.txt
multiprocessing_wrap-0.0.3.dist-info/RECORD
