Metadata-Version: 2.1
Name: multiprocessing-wrap
Version: 0.0.3
Summary: Elegant multiprocessing without the boilerplate and confusing syntax
Home-page: https://github.com/domsleee/multiprocess
Author: Dominic Slee
Author-email: domslee1@gmail.com
License: BSD
Platform: UNKNOWN
Classifier: Programming Language :: Python :: 2
Classifier: Programming Language :: Python :: 3
Requires-Dist: tqdm
Requires-Dist: dill
